wetest/usbtethering/__init__.py
wetest/usbtethering/_log.py
wetest/usbtethering/_version.py
wetest/usbtethering/device_factory.py
wetest/usbtethering/devices/__init__.py
wetest/usbtethering/devices/base.py
wetest/usbtethering/devices/honor.py
wetest/usbtethering/devices/huawei.py
wetest/usbtethering/devices/oppo.py
wetest/usbtethering/devices/redmi.py
wetest/usbtethering/devices/samsung.py
wetest/usbtethering/devices/vivo.py
wetest/usbtethering/devices/xiaomi.py
wetest/usbtethering/exceptions.py
wetest/usbtethering/fastpusher_manager.py
wetest/usbtethering/resources/fastpusher_linux_x86
wetest/usbtethering/uiautomator_manager.py
wetest_usb_tethering-0.0.9.dist-info/METADATA
wetest_usb_tethering-0.0.9.dist-info/WHEEL
wetest_usb_tethering-0.0.9.dist-info/RECORD
