Metadata-Version: 2.4
Name: wetest-usb-tethering
Version: 0.0.9
Summary: Enable and verify Android USB tethering via uiautomator2, with device detection and helpers to download files and extract tar archives over the tethered LAN—useful for transfer testing and automation.
Author: wetest
Author-email: wetest@tencent.com
Requires-Python: >=3.8,<4.0
Classifier: Programming Language :: Python :: 3
Classifier: Programming Language :: Python :: 3.8
Classifier: Programming Language :: Python :: 3.9
Classifier: Programming Language :: Python :: 3.10
Classifier: Programming Language :: Python :: 3.11
Classifier: Programming Language :: Python :: 3.12
Classifier: Programming Language :: Python :: 3.13
Classifier: Programming Language :: Python :: 3.14
Requires-Dist: adbutils (>=2.11.0,<3.0.0)
Requires-Dist: uiautomator2 (>=3.2.9,<4.0.0)
